data_structures/array.py
data_structures/graph.py
data_structures/linked_list.py
data_structures/queue.py
data_structures/stack.py
data_structures/tree.py
data_structures_sago-0.1.0.dist-info/licenses/LICENSE
data_structures_sago-0.1.0.dist-info/METADATA
data_structures_sago-0.1.0.dist-info/WHEEL
data_structures_sago-0.1.0.dist-info/top_level.txt
data_structures_sago-0.1.0.dist-info/RECORD
