Metadata-Version: 2.4
Name: data-structures-sago
Version: 0.1.0
Summary: A pedagogical Python package implementing core data structures from scratch
Author-email: AMMI <csagombaye@aimsammi.org>
License: MIT
Project-URL: Documentation, https://codewithsagomb.github.io/data-structures-python/
Project-URL: Homepage, https://github.com/CodeWithSagomb/data-structures-python
Requires-Python: >=3.6
License-File: LICENSE
Dynamic: license-file
